MediapipeOpenvino/__init__.py
MediapipeOpenvino/calculator/DetectionsToRect.py
MediapipeOpenvino/calculator/ImageConvertOpencv.py
MediapipeOpenvino/calculator/ImageToTensor.py
MediapipeOpenvino/calculator/NonMaximumSuppression.py
MediapipeOpenvino/calculator/RectTransformation.py
MediapipeOpenvino/calculator/SsdAnchorsCalculator.py
MediapipeOpenvino/calculator/TensorsToDetections.py
MediapipeOpenvino/calculator/__init__.py
MediapipeOpenvino/calculator/.ipynb_checkpoints/ImageConvertOpencv-checkpoint.py
MediapipeOpenvino/calculator/.ipynb_checkpoints/ImageToTensor-checkpoint.py
MediapipeOpenvino/calculator/.ipynb_checkpoints/NonMaximumSuppression-checkpoint.py
MediapipeOpenvino/calculator/.ipynb_checkpoints/SsdAnchorsCalculator-checkpoint.py
MediapipeOpenvino/calculator/.ipynb_checkpoints/TensorsToDetections-checkpoint.py
MediapipeOpenvino/face_detection/FaceDetection.py
MediapipeOpenvino/face_detection/__init__.py
MediapipeOpenvino/face_detection/face_detection.bin
MediapipeOpenvino/face_detection/face_detection.mapping
MediapipeOpenvino/face_detection/face_detection.xml
MediapipeOpenvino/face_detection/test.py
MediapipeOpenvino/face_detection/.ipynb_checkpoints/FaceDetection-checkpoint.py
MediapipeOpenvino/face_detection/.ipynb_checkpoints/__init__-checkpoint.py
MediapipeOpenvino/face_detection/.ipynb_checkpoints/face_detection-checkpoint.xml
MediapipeOpenvino/face_detection/.ipynb_checkpoints/test-checkpoint.py
MediapipeOpenvino/face_mesh/FaceMesh.py
MediapipeOpenvino/face_mesh/__init__.py
MediapipeOpenvino/face_mesh/face_mesh.bin
MediapipeOpenvino/face_mesh/face_mesh.mapping
MediapipeOpenvino/face_mesh/face_mesh.xml
MediapipeOpenvino/face_mesh/test.py
MediapipeOpenvino-0.0.2.dist-info/LICENSE
MediapipeOpenvino-0.0.2.dist-info/METADATA
MediapipeOpenvino-0.0.2.dist-info/WHEEL
MediapipeOpenvino-0.0.2.dist-info/top_level.txt
MediapipeOpenvino-0.0.2.dist-info/RECORD
