Metadata-Version: 2.1
Name: MediapipeOpenvino
Version: 0.0.2
Summary: Towards a subset reimplmention of Mediapipe with OpenVINO tool.
Author: qhanson
Author-email: yifeihuang17@gmail.com
License: UNKNOWN
Platform: UNKNOWN
Classifier: Programming Language :: Python :: 3
Classifier: License :: OSI Approved :: MIT License
Classifier: Operating System :: OS Independent
Requires-Python: >=3.6
License-File: LICENSE
Requires-Dist: openvino (>=2022.1.0)
Requires-Dist: opencv-python
